{"_id":{"$oid":"5c25fcc6331e3b1754011c16"},"documentId":52,"status":"waiting For Tagging","handler":"CLMNER","lastSaved":{"$date":"2019-01-04T21:26:37.969Z"},"documentType":"Annual Report","pages":[{"pageId":0,"tags":[{"pt0":[381.0,322.0],"pt1":[1263.0,396.0],"entityType":"Entity Name"},{"pt0":[1433.0,158.0],"pt1":[1501.0,194.0],"entityType":"Stock Code"}],"pageType":""},{"pageId":1,"tags":[],"pageType":""},{"pageId":10,"tags":[],"pageType":""},{"pageId":100,"tags":[],"pageType":""},{"pageId":101,"tags":[],"pageType":""},{"pageId":102,"tags":[],"pageType":""},{"pageId":103,"tags":[],"pageType":""},{"pageId":104,"tags":[{"pt0":[158.0,730.0],"pt1":[1534.0,963.0],"entityType":"Auditor Opinion"},{"pt0":[1294.0,1609.0],"pt1":[1533.0,1635.0],"entityType":"Audit Period"},{"pt0":[623.0,584.0],"pt1":[892.0,615.0],"entityType":"Audit Period"},{"pt0":[879.0,760.0],"pt1":[1129.0,791.0],"entityType":"Audit Period"},{"pt0":[865.0,1469.0],"pt1":[1115.0,1494.0],"entityType":"Audit Period"},{"pt0":[145.7528989770254,370.5103675296991],"pt1":[697.3072056800952,407.4565890313402],"entityType":"Entity Name"},{"pt0":[1124.827768770513,507.7391902500801],"pt1":[1539.1532527532017,549.9634433948128],"entityType":"Entity Name"},{"pt0":[148.3919147985712,547.3244275732669],"pt1":[312.01092529296875,584.2706909179688],"entityType":"Entity Name"}],"pageType":"audit_report"},{"pageId":105,"tags":[],"pageType":""},{"pageId":106,"tags":[],"pageType":""},{"pageId":107,"tags":[{"pt0":[1285.807733884806,230.64252898777232],"pt1":[1539.1532527532017,264.9497346678676],"entityType":"Audit Period"},{"pt0":[156.30896226320857,613.2998231119117],"pt1":[393.82038620232953,655.5240762566443],"entityType":"Name of auditor"}],"pageType":""},{"pageId":108,"tags":[{"pt0":[1185.5251326660662,315.09103527723755],"pt1":[1238.3054490969819,352.0372567788786],"entityType":"Year"},{"pt0":[1425.675572426733,317.73005109878335],"pt1":[1491.6509679653777,349.3982409573328],"entityType":"Year"},{"pt0":[272.42565841122325,246.47662391704705],"pt1":[467.7128292056116,270.22776631095917],"entityType":"Currency"},{"pt0":[1130.1058004136046,2033.090335103546],"pt1":[1235.666433275436,2067.397540783641],"entityType":"Total Equity"},{"pt0":[1375.5342718173629,2035.7293509250917],"pt1":[1486.372936322286,2070.036556605187],"entityType":"Total Equity"}],"pageType":"balance_sheet"},{"pageId":109,"tags":[{"pt0":[383.2643229161464,394.26150992361124],"pt1":[663.0,431.2077314252523],"entityType":"Currency"},{"pt0":[995.5159935147693,499.8221427854428],"pt1":[1064.1304048749598,542.0463959301754],"entityType":"Year"},{"pt0":[1338.5880503157218,502.46115860698853],"pt1":[1417.7585249620956,542.0463959301754],"entityType":"Year"},{"pt0":[921.6235505114872,608.0217914688201],"pt1":[1061.491389053414,644.9680129704611],"entityType":"Total Income"},{"pt0":[1267.3346231339856,605.3827756472743],"pt1":[1409.8414774974583,650.2460446135527],"entityType":"Total Income"},{"pt0":[916.3455188683957,1655.7110726224982],"pt1":[1077.3254839826889,1703.2133574103225],"entityType":"Net Profit"},{"pt0":[1267.3346231339856,1660.9891042655897],"pt1":[1417.7585249620956,1703.2133574103225],"entityType":"Net Profit"}],"pageType":""},{"pageId":11,"tags":[],"pageType":""},{"pageId":110,"tags":[],"pageType":""},{"pageId":111,"tags":[],"pageType":""},{"pageId":112,"tags":[],"pageType":""},{"pageId":113,"tags":[],"pageType":""},{"pageId":114,"tags":[],"pageType":""},{"pageId":115,"tags":[],"pageType":""},{"pageId":116,"tags":[],"pageType":""},{"pageId":117,"tags":[],"pageType":""},{"pageId":118,"tags":[],"pageType":""},{"pageId":119,"tags":[],"pageType":""},{"pageId":12,"tags":[],"pageType":""},{"pageId":120,"tags":[],"pageType":""},{"pageId":121,"tags":[],"pageType":""},{"pageId":122,"tags":[],"pageType":""},{"pageId":123,"tags":[],"pageType":""},{"pageId":124,"tags":[],"pageType":""},{"pageId":125,"tags":[],"pageType":""},{"pageId":126,"tags":[],"pageType":""},{"pageId":127,"tags":[],"pageType":""},{"pageId":128,"tags":[],"pageType":""},{"pageId":129,"tags":[],"pageType":""},{"pageId":13,"tags":[],"pageType":""},{"pageId":130,"tags":[],"pageType":""},{"pageId":131,"tags":[],"pageType":""},{"pageId":132,"tags":[],"pageType":""},{"pageId":133,"tags":[],"pageType":""},{"pageId":134,"tags":[],"pageType":""},{"pageId":135,"tags":[],"pageType":""},{"pageId":136,"tags":[],"pageType":""},{"pageId":137,"tags":[],"pageType":""},{"pageId":138,"tags":[],"pageType":""},{"pageId":139,"tags":[],"pageType":""},{"pageId":14,"tags":[],"pageType":""},{"pageId":140,"tags":[],"pageType":""},{"pageId":141,"tags":[],"pageType":""},{"pageId":142,"tags":[],"pageType":""},{"pageId":143,"tags":[],"pageType":""},{"pageId":144,"tags":[],"pageType":""},{"pageId":145,"tags":[],"pageType":""},{"pageId":146,"tags":[],"pageType":""},{"pageId":147,"tags":[],"pageType":""},{"pageId":148,"tags":[],"pageType":""},{"pageId":149,"tags":[],"pageType":""},{"pageId":15,"tags":[],"pageType":""},{"pageId":150,"tags":[],"pageType":""},{"pageId":151,"tags":[],"pageType":""},{"pageId":152,"tags":[],"pageType":""},{"pageId":153,"tags":[],"pageType":""},{"pageId":154,"tags":[],"pageType":""},{"pageId":155,"tags":[],"pageType":""},{"pageId":156,"tags":[],"pageType":""},{"pageId":157,"tags":[],"pageType":""},{"pageId":158,"tags":[],"pageType":""},{"pageId":159,"tags":[],"pageType":""},{"pageId":16,"tags":[],"pageType":""},{"pageId":160,"tags":[],"pageType":""},{"pageId":161,"tags":[],"pageType":""},{"pageId":162,"tags":[],"pageType":""},{"pageId":163,"tags":[],"pageType":""},{"pageId":164,"tags":[],"pageType":""},{"pageId":165,"tags":[],"pageType":""},{"pageId":166,"tags":[],"pageType":""},{"pageId":167,"tags":[],"pageType":""},{"pageId":168,"tags":[],"pageType":""},{"pageId":169,"tags":[],"pageType":""},{"pageId":17,"tags":[],"pageType":""},{"pageId":170,"tags":[],"pageType":""},{"pageId":171,"tags":[],"pageType":""},{"pageId":172,"tags":[],"pageType":""},{"pageId":173,"tags":[],"pageType":""},{"pageId":174,"tags":[],"pageType":""},{"pageId":175,"tags":[],"pageType":""},{"pageId":176,"tags":[],"pageType":""},{"pageId":177,"tags":[],"pageType":""},{"pageId":178,"tags":[],"pageType":""},{"pageId":179,"tags":[{"pt0":[1132.0,1449.0],"pt1":[1372.0,1475.0],"entityType":"Audit Period"},{"pt0":[827.0,536.0],"pt1":[1111.0,561.0],"entityType":"Audit Period"},{"pt0":[534.0,711.0],"pt1":[807.0,736.0],"entityType":"Audit Period"},{"pt0":[693.0,1309.0],"pt1":[941.0,1334.0],"entityType":"Audit Period"},{"pt0":[158.0,676.0],"pt1":[1534.0,803.0],"entityType":"Auditor Opinion"}],"pageType":"audit_report"},{"pageId":18,"tags":[],"pageType":""},{"pageId":180,"tags":[],"pageType":""},{"pageId":181,"tags":[],"pageType":""},{"pageId":182,"tags":[],"pageType":""},{"pageId":183,"tags":[],"pageType":""},{"pageId":184,"tags":[],"pageType":""},{"pageId":185,"tags":[],"pageType":""},{"pageId":186,"tags":[],"pageType":""},{"pageId":187,"tags":[],"pageType":""},{"pageId":188,"tags":[],"pageType":""},{"pageId":189,"tags":[],"pageType":""},{"pageId":19,"tags":[],"pageType":""},{"pageId":190,"tags":[],"pageType":""},{"pageId":191,"tags":[],"pageType":""},{"pageId":192,"tags":[],"pageType":""},{"pageId":193,"tags":[],"pageType":""},{"pageId":194,"tags":[],"pageType":""},{"pageId":195,"tags":[],"pageType":""},{"pageId":196,"tags":[],"pageType":""},{"pageId":197,"tags":[],"pageType":""},{"pageId":198,"tags":[],"pageType":""},{"pageId":199,"tags":[],"pageType":""},{"pageId":2,"tags":[],"pageType":""},{"pageId":20,"tags":[],"pageType":""},{"pageId":200,"tags":[],"pageType":""},{"pageId":201,"tags":[],"pageType":""},{"pageId":202,"tags":[],"pageType":""},{"pageId":203,"tags":[],"pageType":""},{"pageId":204,"tags":[],"pageType":""},{"pageId":205,"tags":[],"pageType":""},{"pageId":206,"tags":[],"pageType":""},{"pageId":207,"tags":[],"pageType":""},{"pageId":208,"tags":[],"pageType":""},{"pageId":209,"tags":[],"pageType":""},{"pageId":21,"tags":[],"pageType":""},{"pageId":210,"tags":[],"pageType":""},{"pageId":211,"tags":[],"pageType":""},{"pageId":212,"tags":[],"pageType":""},{"pageId":213,"tags":[],"pageType":""},{"pageId":214,"tags":[],"pageType":""},{"pageId":215,"tags":[],"pageType":""},{"pageId":216,"tags":[],"pageType":""},{"pageId":217,"tags":[],"pageType":""},{"pageId":218,"tags":[],"pageType":""},{"pageId":219,"tags":[],"pageType":""},{"pageId":22,"tags":[],"pageType":""},{"pageId":220,"tags":[],"pageType":""},{"pageId":221,"tags":[],"pageType":""},{"pageId":222,"tags":[],"pageType":""},{"pageId":223,"tags":[],"pageType":""},{"pageId":224,"tags":[],"pageType":""},{"pageId":225,"tags":[],"pageType":""},{"pageId":226,"tags":[],"pageType":""},{"pageId":227,"tags":[],"pageType":""},{"pageId":228,"tags":[],"pageType":""},{"pageId":229,"tags":[],"pageType":""},{"pageId":23,"tags":[],"pageType":""},{"pageId":230,"tags":[],"pageType":""},{"pageId":231,"tags":[],"pageType":""},{"pageId":232,"tags":[],"pageType":""},{"pageId":233,"tags":[],"pageType":""},{"pageId":234,"tags":[],"pageType":""},{"pageId":235,"tags":[],"pageType":""},{"pageId":236,"tags":[],"pageType":""},{"pageId":237,"tags":[],"pageType":""},{"pageId":238,"tags":[],"pageType":""},{"pageId":239,"tags":[],"pageType":""},{"pageId":24,"tags":[],"pageType":""},{"pageId":240,"tags":[],"pageType":""},{"pageId":241,"tags":[],"pageType":""},{"pageId":242,"tags":[],"pageType":""},{"pageId":243,"tags":[],"pageType":""},{"pageId":244,"tags":[],"pageType":""},{"pageId":25,"tags":[],"pageType":""},{"pageId":26,"tags":[],"pageType":""},{"pageId":27,"tags":[],"pageType":""},{"pageId":28,"tags":[],"pageType":""},{"pageId":29,"tags":[],"pageType":""},{"pageId":3,"tags":[],"pageType":""},{"pageId":30,"tags":[],"pageType":""},{"pageId":31,"tags":[],"pageType":""},{"pageId":32,"tags":[],"pageType":""},{"pageId":33,"tags":[],"pageType":""},{"pageId":34,"tags":[],"pageType":""},{"pageId":35,"tags":[],"pageType":""},{"pageId":36,"tags":[],"pageType":""},{"pageId":37,"tags":[],"pageType":""},{"pageId":38,"tags":[],"pageType":""},{"pageId":39,"tags":[],"pageType":""},{"pageId":4,"tags":[],"pageType":""},{"pageId":40,"tags":[],"pageType":""},{"pageId":41,"tags":[],"pageType":""},{"pageId":42,"tags":[],"pageType":""},{"pageId":43,"tags":[],"pageType":""},{"pageId":44,"tags":[],"pageType":""},{"pageId":45,"tags":[],"pageType":""},{"pageId":46,"tags":[],"pageType":""},{"pageId":47,"tags":[],"pageType":""},{"pageId":48,"tags":[],"pageType":""},{"pageId":49,"tags":[],"pageType":""},{"pageId":5,"tags":[],"pageType":""},{"pageId":50,"tags":[],"pageType":""},{"pageId":51,"tags":[],"pageType":""},{"pageId":52,"tags":[],"pageType":""},{"pageId":53,"tags":[],"pageType":""},{"pageId":54,"tags":[],"pageType":""},{"pageId":55,"tags":[],"pageType":""},{"pageId":56,"tags":[],"pageType":""},{"pageId":57,"tags":[],"pageType":""},{"pageId":58,"tags":[],"pageType":""},{"pageId":59,"tags":[],"pageType":""},{"pageId":6,"tags":[],"pageType":""},{"pageId":60,"tags":[],"pageType":""},{"pageId":61,"tags":[],"pageType":""},{"pageId":62,"tags":[],"pageType":""},{"pageId":63,"tags":[],"pageType":""},{"pageId":64,"tags":[],"pageType":""},{"pageId":65,"tags":[],"pageType":""},{"pageId":66,"tags":[],"pageType":""},{"pageId":67,"tags":[],"pageType":""},{"pageId":68,"tags":[],"pageType":""},{"pageId":69,"tags":[],"pageType":""},{"pageId":7,"tags":[],"pageType":""},{"pageId":70,"tags":[],"pageType":""},{"pageId":71,"tags":[],"pageType":""},{"pageId":72,"tags":[],"pageType":""},{"pageId":73,"tags":[],"pageType":""},{"pageId":74,"tags":[],"pageType":""},{"pageId":75,"tags":[],"pageType":""},{"pageId":76,"tags":[],"pageType":""},{"pageId":77,"tags":[],"pageType":""},{"pageId":78,"tags":[],"pageType":""},{"pageId":79,"tags":[],"pageType":""},{"pageId":8,"tags":[],"pageType":""},{"pageId":80,"tags":[],"pageType":""},{"pageId":81,"tags":[],"pageType":""},{"pageId":82,"tags":[],"pageType":""},{"pageId":83,"tags":[],"pageType":""},{"pageId":84,"tags":[],"pageType":""},{"pageId":85,"tags":[],"pageType":"audit_report"},{"pageId":86,"tags":[],"pageType":""},{"pageId":87,"tags":[],"pageType":""},{"pageId":88,"tags":[],"pageType":""},{"pageId":89,"tags":[],"pageType":""},{"pageId":9,"tags":[],"pageType":""},{"pageId":90,"tags":[],"pageType":""},{"pageId":91,"tags":[],"pageType":""},{"pageId":92,"tags":[],"pageType":""},{"pageId":93,"tags":[],"pageType":""},{"pageId":94,"tags":[],"pageType":""},{"pageId":95,"tags":[],"pageType":""},{"pageId":96,"tags":[],"pageType":""},{"pageId":97,"tags":[],"pageType":""},{"pageId":98,"tags":[],"pageType":""},{"pageId":99,"tags":[],"pageType":""}],"_class":"com.datalab.taggingInterface.models.Task"}
